{
    "ccolor" :"bright_yellow",
    "url":"http://127.0.0.1:8288/prompt",
    "vaePathSplit":"../ComfyUI/models/vae",
    "vaePath":"../ComfyUI/models/vae/*.safetensors",
    "ckptPathSplit":"../ComfyUI/models/checkpoints/",
    "ckptPath":"../ComfyUI/models/checkpoints/2d/ajisaimix_v20.safetensors",
    "ckptPath":"../ComfyUI/models/checkpoints/2d/99mix_99MixV26.safetensors",
    "ckptPath":"../ComfyUI/models/checkpoints/2d/*.safetensors",
    "loraPath":"../ComfyUI/models/loras/",
    "workflow":"workflow_api.json",
    "lorasFile":"loras.json",
    "ckptPer":1.0,
    "ckptPer":0.0,
    "ckptCnt":16,
    "sampler_name": [
        "euler", "euler_ancestral", "heun", "heunpp2","dpm_2", "dpm_2_ancestral",
         "dpm_fast", "dpm_adaptive", "dpmpp_2s_ancestral", "dpmpp_sde", 
        "dpmpp_2m", "dpmpp_2m_sde",    
        "ddpm",  "ddim", 
    ],
	#"dpmpp_sde_gpu","dpmpp_2m_sde_gpu", "dpmpp_3m_sde_gpu", "dpmpp_3m_sde","lms","uni_pc", "uni_pc_bh2" "lcm",
    "scheduler": [
        "normal", "karras", "exponential",  "simple", ],
		#"sgm_uniform","ddim_uniform"
    "textJoin":", ",
    #"seed": 890115323374972,
    "KSampler":{
        #"seed": 890115323374972,
        #"steps_min": 30,
        #"steps_max": 30,
        #"cfg_min": 1.0,
        #"cfg_max": 8.0,
        #"sampler_name": ["euler", "euler_ancestral", "heun", "heunpp2","dpm_2", "dpm_2_ancestral",
        #    "lms", "dpm_fast", "dpm_adaptive", "dpmpp_2s_ancestral", "dpmpp_sde", "dpmpp_sde_gpu",
        #    "dpmpp_2m", "dpmpp_2m_sde", "dpmpp_2m_sde_gpu", "dpmpp_3m_sde", "dpmpp_3m_sde_gpu", 
        #    "ddpm", "lcm", "ddim", "uni_pc", "uni_pc_bh2"
        #],
        #"scheduler": ["normal", "karras", "exponential", "sgm_uniform", "simple", "ddim_uniform"],
    },
    "DetailerForEachDebug":{
        #"seed": 890115323374972,
        #"steps_min": 30,
        #"steps_max": 30,
        #"cfg_min": 1.0,
        #"cfg_max": 8.0,
        #"sampler_name": [
        #    "euler", "euler_ancestral", "heun", "heunpp2","dpm_2", "dpm_2_ancestral",
        #    "lms", "dpm_fast", "dpm_adaptive", "dpmpp_2s_ancestral", "dpmpp_sde", "dpmpp_sde_gpu",
        #    "dpmpp_2m", "dpmpp_2m_sde", "dpmpp_2m_sde_gpu", "dpmpp_3m_sde", "dpmpp_3m_sde_gpu", 
        #    "ddpm", "lcm", "ddim", "uni_pc", "uni_pc_bh2"
        #],
        #"scheduler": ["normal", "karras", "exponential", "sgm_uniform", "simple", "ddim_uniform"],
        "denoise_min": 0.20,
        "denoise_max": 0.4,
    },
    "cuda" : {
        "ckptCnt":32,
        "itemCnt":4,
        "queue_cnt":1,
		"KSampler":{
			#"steps": 40,
			"steps_min": 30,
			"steps_max": 40,
		},
		"DetailerForEachDebug":{
            #"steps": 20,
			"steps_min": 15,
			"steps_max": 20,
		},
		"EmptyLatentImage":{
			"width": 384,
			"height": 768,
		},
    },
    "cpu" : {
        "ckptCnt":16,
        "itemCnt":2,
        "queue_cnt":1,
		#"steps": 25,
		"KSampler":{
			"steps": 20,
			"steps_min": 20,
			"steps_max": 20,
		},
		"DetailerForEachDebug":{
			"steps": 15,
		},
		"EmptyLatentImage":{
			"width": 360,
			"height": 720,
		},
    },
    "stop_at_clip_layer_min": -2,
    "stop_at_clip_layer_max": -1,
    #"steps_min": 20,
    #"steps_max": 20,
    #"steps": 30,
    "cfg_min": 2.0,
    "cfg_max": 8.0,
    "listMatch": [
"（梣）Morgan",
"00_RioTera_V1b-000005",
"02Zerotwo_v10",
"2ke_v10",
"morinoRinzeTHEIDOLMSTER_v10",
"2♥ex-sasha",
"FireflyHSR-07",
"30_chuchu",
"lilianna_centostella",
"AZKi_v10",
"OldrinZevon-10",
"azki diva1",
"azki diva2",
"AAG-golaniyule",
"31tanD8V1_e6",
"3DXingtong_v01Test1",
"6thNekomusumeGegegeNo_v10",
"71TT0OP",
"[hikari]saros_eresh_kurnugias_v1",
"aceTrainerXYPokemonXY_v10",
"Alex(remake)",
"araragiTsukihiLora_v1",
"araragiTsukihiLora_v1-monsterSexActLora79_v10",
"araragiTsukihiLora_v1-transformation",
"araragiTsukihiLora_v1-hyper_penetration_stomach_bulge_v8",
"aliciaIsekaiOjisan_v10",
"amatsuka_watayuki",
"an94GirlsFrontline_10",
"anastasia_(idolmaster)_v2",
"annaRedoOfHealer_v10",
"anastasiaTHEIdolmSTER_anastasiaV10",
"Araragi Tsukihi",
"Araragi Tsukihi-ddkb_v1",
"Belladonna-hang",
"monogatari_all_v2-tsukihi",
"monogatari_all_v2-sengoku nadeko",
"PrincessConnect_Hatsune",
"Amagamine Renna(rr)",
"VioletFate-10",
"lemrina",
"Belladonna",
"MitsuruKirijo",
"Card Captor Sakura Anime",
"carolMalusDienheimSenki_v11",
"carolMalusDienheimSenki_v11-hyper_penetration_stomach_bulge_v8all",
"carolMalusDienheimSenki_v11-Deepthroat",
"carolMalusDienheimSenki_v11-sex_toy_transformation",
"carolMalusDienheimSenki_v14",
"celine_(fire_emblem)_v1",
"CHAR-DianaCavendish-aki-000024",
"CHAR-DianaCavendish-bdsm_frame",
"CHAR-DianaCavendish-DbDildo",
"CHAR-DianaCavendish-Deepthroat",
"CHAR-DianaCavendish-dildoV1",
"CHAR-DianaCavendish-hang",
"CHAR-DianaCavendish-hyper_penetration_stomach_bulge_v8nice",
"CHAR-DianaCavendish-LargeInsertion-v1",
"CHAR-DianaCavendish-Luoxuan_V2-000028",
"CHAR-DianaCavendish-obp-000050",
"CHAR-DianaCavendish-onahole_personality_v17-microwaist",
"CHAR-DianaCavendish-onahole_personality_v17-obp-000050-microwaist",
"CHAR-DianaCavendish-onahole_personality_v17",
"CHAR-DianaCavendish-osofel",
"CHAR-DianaCavendish-set1",
"CHAR-DianaCavendish-set2",
"CHAR-DianaCavendish-set3",
"CHAR-DianaCavendish-set4",
"CHAR-DianaCavendish-sex from behind",
"CHAR-DianaCavendish-sex_toy_transformation-microwaist",
"CHAR-DianaCavendish-sex_toy_transformation-obp-000050-microwaist",
"CHAR-DianaCavendish-sex_toy_transformation",
"CHAR-DianaCavendish",
"Chitose_V6-E10_(SetoYuuki)",
"Chkuriyama",
"ClaraStarRailV1",
"cogita_pokemon",
"cyan_30-000003-standsex",
"cyan_30-000003-hang",
"cyan_30-000003-Luoxuan_V2-000028",
"cyan_30-000003-obp-000050",
"cyan_30-000003-hyper_penetration_stomach_bulge_v8",
"cyan_30-000003-set3",
"cyan_30-000003-transformation",
"cyan_30-000003-set4",
"cyan_30-000003",
"cyrille-nvwls-v1",
"daidoujiTomoyo_v01",
"daili_v20",
"Diana_Cavendish",
"Diana_Cavendish_2",
"diana_cavendish_multimerge",
"diana_cavendish_multimerge-sex_toy_transformation",
"Dorothy-10",
"eft_goblin_guild-03",
"eiko-10",
"Ellen Baker(alt)",
"elysia4in1Lora_v10",
"elysia5in1Lora_v20",
"elysia_",
"EmiKino-10",
"EmiKino-10-sex_toy_transformation",
"EmiKino-10-sex_toy_transformation-Deepthroat",
"emilia_lapisrelights",
"Eris-10-aki-000024",
"Eris-10-bdsm_frame",
"Eris-10-BondagePoleV1",
"Eris-10-dildoV1",
"Eris-10-fingering_3rd_v1",
"Eris-10-hunged_girl",
"Eris-10-hyper_penetration_stomach_bulge_v8",
"Eris-10-hyper_penetration_stomach_bulge_v8nice",
"Eris-10-Luoxuan_V2",
"Eris-10-transformation",
"Eris-10-set4",
"Eris-10-standsex",
"Eris-10",
"Eris0.32-000008",
"Eris0.32-000008-monsterSexActLora79_v10",
"Eris0.32-000008-standsex",
"Eris0.32-000008-Deepthroat",
"Eris0.32-000008-transformation",
"Eris0.32-000008-transformation-obp-000050",
"Eris0.32-000008-obp-000050",
"Erispheria",
"Estelle",
"feiyufuV1",
"frenda seivelun s3-lora-nochekaiser",
"frenda_seivelun",
"FushikawaKokoroXL-000096",
"GishanV4-10",
"Golding",
"hammannNotRetrofitAzur_adafactor",
"hasumin",
"herio hanamori manga-lora-nochekaiser",
"Honolulu",
"Hood-hang",
"Hood-hyper_penetration_stomach_bulge_v8absurd",
"Hood-monsterSexActLora79_v10",
"Hood-monsterSexActLora79_v10-sex_toy_transformation",
"Hood-sex_toy_transformation",
"Hood-sex_toy_transformation-Deepthroat",
"Hood-set4",
"Hood",
"hood_azurlane",
"Hood_v3",
"hoodAzurLane_v10-obp-000050",
"hoodAzurLane_v10-sex_toy_transformation-obp-000050",
"hoodAzurLane_v10-sex_toy_transformation",
"hoodAzurLane_v10",
"hornet-10",
"ilu_fluor_v1",
"Inagaki Sae(sk)",
"Isabelle",
"iseriaEpicSeven_v1",
"itzyYuna_v10",
"Jasminka_Antonenko",
"JAV_Rina_I_v1.0",
"jessicaGranblue_v10",
"JiaranDianaLoraASOUL_v20SingleCostume",
"jougasaki_mika_v1-hyper_penetration_stomach_bulge_v8",
"jougasaki_mika_v1-standsex",
"jougasaki_mika_v1-Luoxuan_V2",
"jougasaki_mika_v1",
"KaliDN-10",
"kanzaki ranko_Loha",
"Karin-CC",
"kayoko15",
"kmiyukoV2",
"konosuba_eris-09",
"konosuba_wiz-10",
"koseki-bijou",
"kozueYusa",
"Laura Latour",
"Linnea",
"mahjongsoul_fuji",
"MahoukaMayumi-v1-06",
"MahoukaMiyuki-v1-04-fingering_3rd_v1",
"MahoukaMiyuki-v1-04-kimono",
"MahoukaMiyuki-v1-04-Mirage Bat",
"MahoukaMiyuki-v1-04",
"majoNoTabitabiElaina_v20",
"makina69_tzuyu_v1.0",
"Mari-10",
"Marianne_Vi_Britannia",
"Marin-10",
"Marina_Fear__Hunger_2_Termina",
"MaristheDarkWitch-10",
"MasterArtoria-10",
"MayaYotsuba-10-Luoxuan_V2-BondagePoleV1",
"MayaYotsuba-10",
"mayumi-mahouka-01",
"merylTowerOfFantasy_v11",
"millia_rage",
"milliaRageGuiltyGear_1",
"minami2",
"Miroku_Renge-10",
"mitsukiV1",
"miyuki-mahouka-01-set4",
"miyuki-mahouka-01",
"modelyua",
"Myrrh_fe_v1",
"mzdl",
"nailin_wizard",
"Naruse_Maria",
"Nasya-000015",
"no",
"originalCatGirl_v10",
"ouroKroniiHololive_v10",
"paSanBocchiTheRock_v10-hang",
"paSanBocchiTheRock_v10",
"plana-blue-archive",
"pr-rainbow_otoha_v1.0b",
"Priscilla",
"projectSekaiAsahina_mafuyuLoconFinal",
"Puddingcess_YGO-10",
"qingque-str-v2cr",
"queenElizabethAzur_queenElizabethV1",
"raidenShogunGenshin_raidenv1",
"ranalora-10-fingering_3rd_v1",
"ranalora-10",
"RedYor-hang",
"RedYor-set4",
"RedYor",
"reimuEndou_main",
"reines_v2",
"richelieu_azurlane",
"riko_pokemon",
"Riruru",
"RocoHanda-03",
"rwby_weissschnee-12",
"sakagami tomoyo_v1_04",
"Sakuragi_Koharu",
"satonoDiamond_v10",
"SeeThroughMaid_v1",
"seolhyunFromAOA_v10",
"SerenaLora-10",
"serenaPokemon_v10",
"side-deepthroat-v3-wasabiya-sex_toy_transformation",
"set1",
"ShadowverseBrilliantFairyV1-000021",
"sharon_holygrail",
"sharon_holygrail-transformation",
"sharon_holygrail-standsex",
"sharon_holygrail-monsterSexActLora79_v10",
"sharon_holygrail-hyper_penetration_stomach_bulge_v8",
"sharon_holygrail-set4",
"Shiba MiyukiV1",
"ShibaMiyuki",
"ShibaMiyuki-transformation",
"ShibaMiyuki-standsex",
"ShibaMiyuki-BondagePoleV1",
"ShibaMiyuki-hyper_penetration_stomach_bulge_v8",
"ShibaMiyuki-monsterSexActLora79_v10",
"shijou_takane_v1",
"ShiLuHonkai",
"shinshuu_maru_kantaicollection",
"shiromiIoriLora_v1",
"shizuku-mahouka-01",
"silentMagicianYuGiOh_v10",
"Sono Bisque Doll wa Koi wo Suru - Marin Kitagawa V2",
"sorasaki hina(dress)",
"SougetsuEli_v10",
"Strelitzia-10",
"Strelitzia-10-transformation",
"Strelitzia",
"sweet_attire_style2_v1",
"tachibana_arisu_v1",
"tanya",
"tofGirlFromEvent_v3",
"Toki_V2.0",
"tokisaki_kurumi_v1-transformation",
"tokisaki_kurumi_v1-standsex",
"tokisaki_kurumi_v1-hyper_penetration_stomach_bulge_v8",
"tokisaki_kurumi_v1-hang",
"tokisaki_kurumi_v1-obp-000050",
"tokisaki_kurumi_v1-set4",
"tokisaki_kurumi_v1",
"TokisakiKurumi-10",
"tomoyo_V1Epoch6-Luoxuan_V2-000028",
"tomoyo_V1Epoch6-transformation",
"tomoyo_V1Epoch6-ddkb_v1",
"tomoyo_V1Epoch6-set4",
"tomoyo_V1Epoch6",
"tomoyo_v3_locon-hang",
"tomoyo_v3_locon-obp-000050",
"tomoyo_v3_locon",
"TomoyoDaidoji-128",
"utsumierice-10",
"victorian_maid-1.0",
"virtualgirlAim_v30",
"Weiss_RWBY_AnyLora",
"weiss_schnee-10",
"weiss_schnee-hang",
"weiss_schnee",
"whiteNun_v10",
"WitchFateEOD-10-b4ll3th33ls",
"WitchFateEOD-10",
"Wiz - Konosuba v1",
"wiz_(konosuba)_v1",
"YaeKokonoe-10",
"YayoiKancolle",
"yor briar s1-lora-nochekaiser",
"yor briar s1-lyco-nochekaiser",
"yor4-06-hang",
"yor4-06",
"Yor_Briar-hang",
"Yor_Briar",
"yor_briar_spyxfamily-hang",
"yor_briar_spyxfamily-hunged_girl",
"yor_briar_spyxfamily",
"yor_forger_v1-hang",
"yor_forger_v1-set4",
"yor_forger_v1",
"YorLora-10",
"YueAyase-v1-aki-000024",
"YueAyase-v1-bdsm_frame",
"YueAyase-v1-dildoV1",
"YueAyase-v1-sex_toy_transformation",
"YueAyase-v1-monsterSexActLora79_v10",
"YueAyase-v1-hang",
"YueAyase-v1-hunged_girl",
"YueAyase-v1-hyper_penetration_stomach_bulge_v8",
"YueAyase-v1-hyper_penetration_stomach_bulge_v8nice",
"YueAyase-v1-LargeInsertion-v1",
"YueAyase-v1-Luoxuan_V2",
"YueAyase-v1-obp-000050",
"YueAyase-v1-set4",
"YueAyase-v1",
"yuGiOhTraptrixNepenthes_v10",
"yuGiOhTraptrixNepenthes_v10-obp-000050",
"YunaFloralFallal-10",
"yurisa chan_v1",
"MiriaBaccano-08",
"KannagiLokiLora-10v2",
"ceylon_arknights",
"serena_(yu-gi-oh!)_v1",
"pokemon serena-lora-nochekaiser",
"serena_(pokemon)_v2-aaserena",
"serena_(pokemon)_v2-bbserena",
"serena_(pokemon)_v2-ccserena",
"serena_(pokemon)_v2-ddserena",
"serena_(pokemon)_v2-eeserena",
"KallenNun-10",
"Kai_Dai no Daibouken_Leona_20240331",
"mousse_arknights",
"RitaRQ-10",
"PekoMamaLora-10",
"kalliope-000022",
"yurisaLora_v20",
"PrincessConnect_Karyl",
"yurisaLora_v20-leheng_re",
"ZaraKotobuki-10",
"ZoeKyonyuu-10",
"zs_NagiPQ2",
"佩琳·H·克洛斯特曼--强袭魔女_v1.0-set4",
"佩琳·H·克洛斯特曼--强袭魔女_v1.0",
"约尔·福杰1Ve",
"约尔4V",
"黑金",
"유사 코즈에",
"포켓몬_봄이",
    #],"listMatch": [
    ],"listMatch1": [
        "FushikawaKokoroXL-000096",
    ],
	"shuffle":False,
    "shuffle":true,
	"positive": {
        "pose":"{kneeling,kneeling pose|sit|man behind girl|7::},",
        "nsfw":"nsfw,",
        "style":"{1-3$$anime style|2D|anime},",
        "insertion":"(multiple insertions, large insertion, {vaginal|anal|} object insertion, impossible object insertion, object insertion:1.25), {Pregnant,|7:: }",
        "sex":"{(sex),|}",
        "asphyxiation":"{(asphyxiation:1.0),|}",
        "rolling eyes":"{3::(rolling eyes:1.1250),|}",
        "blank eyes":"{3::(blank eyes:1.0),|}",
        "handcuffs":"{3::(handcuffs:1.0),|}",
        "boy":"1boy,",
        "boy":"{2boy,|1boy,|}",
        "girl":"1girl,",
        #"gag":"{ball gag,|7:: }",
        "face":"{ahegao,|}{orgasm ,|}",
        "quality":"masterpiece , best quality , detailed face,",
        "looking":"looking at viewer,",
        #"view":"{cowboy shot,|} {from side,|9::}",
        #"shot":"full body, ",
        "shot":"cowboy shot, ",
        "shot":"{cowboy shot,|} ",
        "view":"{from side,|7::}",
        "chest":"__chest__, thin waist,",
        #"char":"1girl,  __char__, ",
        #"body":"__chest__, thin waist, {<lora:microwaistV05:__0.25_0.75__:1.0>,|3::}",
        #"sex":"sex, large insertion, dildo riding , dildo, object insertion,{arms behind back, bound arms, bound bdsm, bdsm, |} {__insertion__,|} ",
        "dress":"{__dress_set__,|} ",
        "frills":"{frills,|} {frilled dress,|} {frilled skirt,|} {frilled sleeves,|} ",
        "revealing":"",
        #"open_dress":"{(open_dress:1.0), (Undressing:1.1), Nipples, (Pussy:1.1), {(navel:1.0),|}|2::}",
        "exposure":"(exposure:1.0), breasts exposure, breasts out, nipples exposure, pussy exposure, {revealing clothes,|} ",
        "shoulder":"off shoulder, bare shoulder, Droptop, strapless dress, chest open, {See Through,|7::}",
        #"concept":"{3::__concept__,|1::__concept__,__concept__,}  "
    },
    "negative" : {
        "quality":"lowres, worst quality, low quality,  from torso down, (monochrome:1.1), zombie , (blurry),",
        "view":"(multiple views:1.25), (multiple viewer:1.25),  (cropped:1.25), face only,  lower body,  facial,",
        "bad":" bad anatomy, bad hands,   missing fingers, extra digit, fewer digits, speech bubble, ",
        "nude":"{nude,|}",
        "etc":"text, sinature, stamp, watermark, error, jpeg artifacts, signature,  username,",
        "realistic":"{realistic,|}",
        "smile":"smile,",
        "embedding":"{-4$$embedding:FastNegativeV2.pt|embedding:NGH.safetensors|embedding:bad_prompt_version2-neg.pt|embedding:negative_hand-neg|embedding:nncursedV0-neg.pt|embedding:badquality.pt|embedding:bad-picture-chill-75v.pt|embedding:neg_grapefruit.pt|embedding:ParaNegative.safetensors|embedding:easynegative.safetensors|embedding:EasyNegativeV2.safetensors},",
    },
    "loras":{    },
    "lorasDic":{    },
    #"lorasUpdate":false,
    #"lorasUpdate":true,
    "SaveImage1":false,
    "SaveImage1":true,
    "SaveImage2":false,
    "SaveImage2":true,
    "lora show":true,
    "lora show":false,
    "skip show":true,
    "skip show":false,
    "prompt show":true,
    "prompt show":false,
    "setup show":true,
    "setup show":false,
    "jitem show":true,
    "jitem show":false,
    "queue_prompt":false,
    "queue_prompt":true,
    
}